starknet_py/__init__.py
starknet_py/cairo/__init__.py
starknet_py/cairo/felt.py
starknet_py/common.py
starknet_py/compile/__init__.py
starknet_py/compile/compiler.py
starknet_py/constants.py
starknet_py/contract.py
starknet_py/net/__init__.py
starknet_py/net/account/__init__.py
starknet_py/net/account/account_client.py
starknet_py/net/account/compiled_account_contract.py
starknet_py/net/client.py
starknet_py/net/client_errors.py
starknet_py/net/client_models.py
starknet_py/net/client_utils.py
starknet_py/net/full_node_client.py
starknet_py/net/gateway_client.py
starknet_py/net/http_client.py
starknet_py/net/l1/__init__.py
starknet_py/net/l1/contracts.py
starknet_py/net/l1/messages.py
starknet_py/net/l1/starknet_l1_abi.py
starknet_py/net/models/__init__.py
starknet_py/net/models/address.py
starknet_py/net/models/chains.py
starknet_py/net/models/transaction.py
starknet_py/net/networks.py
starknet_py/net/schemas/__init__.py
starknet_py/net/schemas/common.py
starknet_py/net/schemas/gateway.py
starknet_py/net/schemas/rpc.py
starknet_py/net/signer/__init__.py
starknet_py/net/signer/base_signer.py
starknet_py/net/signer/stark_curve_signer.py
starknet_py/proxy_check.py
starknet_py/transaction_exceptions.py
starknet_py/transactions/__init__.py
starknet_py/transactions/declare.py
starknet_py/transactions/deploy.py
starknet_py/utils/__init__.py
starknet_py/utils/crypto/__init__.py
starknet_py/utils/crypto/facade.py
starknet_py/utils/crypto/libcrypto_c_exports.dylib
starknet_py/utils/data_transformer/__init__.py
starknet_py/utils/data_transformer/data_transformer.py
starknet_py/utils/data_transformer/execute_transformer.py
starknet_py/utils/docs.py
starknet_py/utils/sync/__init__.py
starknet_py/utils/sync/sync.py
starknet_py/utils/types.py
starknet_py-0.5.1a0.dist-info/LICENSE.txt
starknet_py-0.5.1a0.dist-info/WHEEL
starknet_py-0.5.1a0.dist-info/METADATA
starknet_py-0.5.1a0.dist-info/RECORD
