Metadata-Version: 2.1
Name: starknet-py
Version: 0.5.1a0
Summary: A python SDK for StarkNet
Home-page: https://github.com/software-mansion/starknet.py
License: MIT
Author: Tomasz Rejowski
Author-email: tomasz.rejowski@swmansion.com
Requires-Python: >=3.8,<3.10
Classifier: License :: OSI Approved :: MIT License
Classifier: Programming Language :: Python :: 3
Classifier: Programming Language :: Python :: 3.8
Classifier: Programming Language :: Python :: 3.9
Provides-Extra: docs
Provides-Extra: eth-tester
Requires-Dist: asgiref (>=3.4.1,<4.0.0)
Requires-Dist: cairo-lang (==0.10.0)
Requires-Dist: crypto-cpp-py (>=1.0.4,<2.0.0)
Requires-Dist: enum-tools[sphinx] (==0.9.0); extra == "docs"
Requires-Dist: marshmallow (>=3.15.0,<4.0.0)
Requires-Dist: marshmallow-oneofschema (>=3.0.1,<4.0.0)
Requires-Dist: sphinx (>=4.3.1,<5.0.0); extra == "docs"
Requires-Dist: typing-extensions (>=4.3.0,<5.0.0)
Project-URL: Documentation, https://starknetpy.rtfd.io/
Project-URL: Repository, https://github.com/software-mansion/starknet.py
